kbackgroundtask/__init__.py
kbackgroundtask/admin.py
kbackgroundtask/apps.py
kbackgroundtask/models.py
kbackgroundtask/signals.py
kbackgroundtask/tasks.py
kbackgroundtask/tests.py
kbackgroundtask/views.py
kbackgroundtask/locale/en/LC_MESSAGES/django.mo
kbackgroundtask/locale/en/LC_MESSAGES/django.po
kbackgroundtask/locale/fi/LC_MESSAGES/django.mo
kbackgroundtask/locale/fi/LC_MESSAGES/django.po
kbackgroundtask/management/__init__.py
kbackgroundtask/management/commands/__init__.py
kbackgroundtask/management/commands/kill_unresponsive_tasks.py
kbackgroundtask/migrations/0001_initial.py
kbackgroundtask/migrations/__init__.py
kcommunication/__init__.py
kcommunication/admin.py
kcommunication/apps.py
kcommunication/helpers.py
kcommunication/models.py
kcommunication/sendgrid.py
kcommunication/tasks.py
kcommunication/tests.py
kcommunication/views.py
kcommunication/migrations/__init__.py
django_kcommunication-1.2.1.dist-info/LICENSE.txt
django_kcommunication-1.2.1.dist-info/METADATA
django_kcommunication-1.2.1.dist-info/WHEEL
django_kcommunication-1.2.1.dist-info/top_level.txt
django_kcommunication-1.2.1.dist-info/RECORD
